indicators.cpython-37m-darwin.so
src/__init__.py
src/indicators.c
src/indicators.pyx
tests/__init__.py
tests/test_functions.py
cython_indicators-1.0.0.dist-info/LICENSE
cython_indicators-1.0.0.dist-info/METADATA
cython_indicators-1.0.0.dist-info/WHEEL
cython_indicators-1.0.0.dist-info/top_level.txt
cython_indicators-1.0.0.dist-info/RECORD
