Metadata-Version: 2.1
Name: cython-indicators
Version: 1.0.0
Summary: Indicator functions using cython
Home-page: https://github.com/VolaTrade/Technical-Indicators
Author: Ethen Pociask
Author-email: epociask@volatrade.com
License: UNKNOWN
Platform: UNKNOWN
Classifier: Programming Language :: Python :: 3
Classifier: License :: OSI Approved :: MIT License
Classifier: Operating System :: OS Independent
Classifier: Intended Audience :: Developers
Classifier: Topic :: Software Development :: Libraries :: Python Modules
Classifier: Topic :: Internet
Requires-Python: >=3.6
Requires-Dist: Cython
Requires-Dist: numpy
